resilient_caller/__init__.py
resilient_caller/exceptions.py
resilient_caller/send_requests.py
resilient_caller/utils.py
resilient_caller/wrapper.py
resilient_caller-0.2.2.dist-info/LICENSE
resilient_caller-0.2.2.dist-info/METADATA
resilient_caller-0.2.2.dist-info/WHEEL
resilient_caller-0.2.2.dist-info/top_level.txt
resilient_caller-0.2.2.dist-info/RECORD
