Metadata-Version: 2.1
Name: resilient-caller
Version: 0.2.2
Summary: A Python package to retry function calls with custom logic and handling.
Home-page: https://github.com/glizzykingdreko/resilient_caller
Author: glizzykingdreko
Author-email: glizzykingdreko@protonmail.com
Classifier: Development Status :: 3 - Alpha
Classifier: Intended Audience :: Developers
Classifier: License :: OSI Approved :: MIT License
Classifier: Operating System :: OS Independent
Classifier: Programming Language :: Python :: 3
Classifier: Programming Language :: Python :: 3.6
Classifier: Programming Language :: Python :: 3.7
Classifier: Programming Language :: Python :: 3.8
Classifier: Programming Language :: Python :: 3.9
Requires-Python: >=3.6
License-File: LICENSE
Requires-Dist: requests
Requires-Dist: asyncio
